patchparser/__init__.py
patchparser/github_parser.py
patchparser/github_parser_local.py
patchparser-0.0.3.dist-info/LICENSE
patchparser-0.0.3.dist-info/METADATA
patchparser-0.0.3.dist-info/WHEEL
patchparser-0.0.3.dist-info/top_level.txt
patchparser-0.0.3.dist-info/RECORD
