Metadata-Version: 2.1
Name: patchparser
Version: 0.0.3
Summary: A python package to extract features from a commit patch.
Author-email: Trevor Dunlap <tdunlap607@gmail.com>
Project-URL: Homepage, https://github.com/tdunlap607/patchparser
Project-URL: Bug Tracker, https://github.com/tdunlap607/patchparser/issues
Classifier: Programming Language :: Python :: 3
Classifier: License :: OSI Approved :: The Unlicense (Unlicense)
Classifier: Operating System :: OS Independent
Requires-Python: >=3.7
License-File: LICENSE
Requires-Dist: requests
Requires-Dist: GitPython
